README
setup.py
./smorgasbord/__init__.py
./smorgasbord/contextutil.py
./smorgasbord/loader.py
django_smorgasbord.egg-info/PKG-INFO
django_smorgasbord.egg-info/SOURCES.txt
django_smorgasbord.egg-info/dependency_links.txt
django_smorgasbord.egg-info/top_level.txt
smorgasbord/__init__.py
smorgasbord/contextutil.py
smorgasbord/loader.py
smorgasbord/languages/__init__.py
smorgasbord/languages/cheetahsupport.py
smorgasbord/languages/jinja2support.py
smorgasbord/languages/makosupport.py
smorgasbord/languages/stmlsupport.py